{
  "version": 1,
  "description": "Crediti e provenienza delle immagini utilizzate nelle card dei Comuni.",
  "images": [
    {
      "municipality": "*",
      "file": "assets/placeholder-comune.svg",
      "type": "placeholder",
      "author": "Cilentomania APS",
      "source": "Cilentomania HUB",
      "license": "Asset interno",
      "notes": "Placeholder temporaneo 800 x 500 utilizzato fino all'inserimento delle fotografie approvate."
    },
    {
      "id": "IMG-AGROPOLI-CARD-001",
      "municipality": "Agropoli",
      "file": "images/comuni/agropoli.webp",
      "type": "card",
      "title": "Panorama di Agropoli",
      "subject": "Panorama di Agropoli con il promontorio urbano e il porto",
      "description": "Veduta panoramica di Agropoli con il promontorio urbano e il porto.",
      "category": "panorama",
      "author": "RealNordyNed",
      "source": "Wikimedia Commons",
      "source_url": "https://commons.wikimedia.org/wiki/File:Agropoli_Panorama_2015.jpg",
      "license": "CC BY-SA 4.0",
      "license_url": "https://creativecommons.org/licenses/by-sa/4.0/",
      "consulted_at": "2026-07-17",
      "alt": "Panorama di Agropoli con il promontorio urbano e il porto",
      "changes": "Ritaglio orizzontale 8:5, ridimensionamento a 800 x 500 pixel e conversione WebP.",
      "notes": "Opera derivata distribuita secondo i termini della licenza CC BY-SA 4.0; attribuzione all'autore richiesta."
    },
    {
      "id": "IMG-AGROPOLI-COVER-001",
      "municipality": "Agropoli",
      "file": "images/comuni/agropoli-copertina-final.webp",
      "type": "cover",
      "title": "Agropoli dagli scaloni del borgo",
      "subject": "Veduta di Agropoli dagli scaloni del borgo verso la città e il porto",
      "description": "Veduta dagli scaloni del borgo verso la città di Agropoli e il porto.",
      "category": "scorci caratteristici",
      "author": "Carlo Iannuzzi (account Wikimedia Mujaidin)",
      "source": "Wikimedia Commons",
      "source_url": "https://commons.wikimedia.org/wiki/File:Agropoli_-_Gli_Scaloni_e_il_Porto.JPG",
      "license": "CC BY-SA 3.0",
      "license_url": "https://creativecommons.org/licenses/by-sa/3.0/",
      "consulted_at": "2026-07-17",
      "alt": "Veduta di Agropoli dagli scaloni del borgo verso la città e il porto",
      "changes": "Ritaglio privo della scritta presente nell'originale, ridimensionamento a 800 x 500 pixel e conversione WebP.",
      "notes": "Opera derivata distribuita secondo i termini della licenza CC BY-SA 3.0; attribuzione all'autore richiesta."
    },
    {
      "id": "IMG-AGROPOLI-GALLERY-001",
      "municipality": "Agropoli",
      "file": "images/comuni/agropoli-castello.webp",
      "type": "gallery",
      "title": "Castello angioino-aragonese",
      "subject": "Veduta esterna del Castello angioino-aragonese di Agropoli",
      "description": "Le mura e le torri del castello che domina il borgo antico di Agropoli.",
      "category": "monumenti",
      "author": "Hidely",
      "source": "Wikimedia Commons",
      "source_url": "https://commons.wikimedia.org/wiki/File:Castello_di_Agropoli.jpg",
      "license": "CC BY-SA 4.0",
      "license_url": "https://creativecommons.org/licenses/by-sa/4.0/",
      "consulted_at": "2026-07-17",
      "alt": "Veduta esterna del Castello angioino-aragonese di Agropoli",
      "changes": "Ritaglio orizzontale 3:2, ridimensionamento a 1600 x 1067 pixel e conversione WebP.",
      "notes": "Opera derivata distribuita secondo i termini della licenza CC BY-SA 4.0; attribuzione all'autore richiesta."
    },
    {
      "id": "IMG-AGROPOLI-GALLERY-002",
      "municipality": "Agropoli",
      "file": "images/comuni/agropoli-trentova.webp",
      "type": "gallery",
      "title": "Spiaggia di Trentova",
      "subject": "Spiaggia di Trentova e paesaggio costiero di Agropoli",
      "description": "La baia di Trentova con il suo caratteristico scoglio e il profilo della costa cilentana.",
      "category": "spiagge",
      "author": "Alessandra Boccone",
      "source": "Wikimedia Commons",
      "source_url": "https://commons.wikimedia.org/wiki/File:Spiaggia_di_Trentova,_Agropoli_(SA).jpg",
      "license": "CC BY-SA 4.0",
      "license_url": "https://creativecommons.org/licenses/by-sa/4.0/",
      "consulted_at": "2026-07-17",
      "alt": "Spiaggia di Trentova ad Agropoli con il caratteristico scoglio",
      "changes": "Ritaglio orizzontale 3:2, ridimensionamento a 1600 x 1067 pixel e conversione WebP.",
      "notes": "Opera derivata distribuita secondo i termini della licenza CC BY-SA 4.0; attribuzione all'autrice richiesta."
    },
    {
      "id": "IMG-AGROPOLI-GALLERY-003",
      "municipality": "Agropoli",
      "file": "images/comuni/agropoli-piazza-costantinopoli.webp",
      "type": "gallery",
      "title": "Piazza Madonna di Costantinopoli",
      "subject": "Insegna di Piazza Madonna di Costantinopoli nel borgo di Agropoli",
      "description": "Un dettaglio della piazza dedicata alla Madonna di Costantinopoli nel centro storico.",
      "category": "centro storico",
      "author": "Bernard Gagnon (account Wikimedia Bgag)",
      "source": "Wikimedia Commons",
      "source_url": "https://commons.wikimedia.org/wiki/File:Piazza_Madonna_di_Costantinopoli_(Agropoli).jpg",
      "license": "CC BY 4.0",
      "license_url": "https://creativecommons.org/licenses/by/4.0/",
      "consulted_at": "2026-07-17",
      "alt": "Insegna di Piazza Madonna di Costantinopoli nel centro storico di Agropoli",
      "changes": "Ritaglio orizzontale 3:2, ridimensionamento a 1600 x 1067 pixel e conversione WebP.",
      "notes": "Opera derivata distribuita secondo i termini della licenza CC BY 4.0; attribuzione all'autore richiesta."
    },
    {
      "id": "IMG-AGROPOLI-GALLERY-004",
      "municipality": "Agropoli",
      "file": "images/comuni/agropoli-porto.webp",
      "type": "gallery",
      "title": "Porto di Agropoli",
      "subject": "Veduta del porto turistico di Agropoli",
      "description": "Il porto di Agropoli osservato dall'alto, con le imbarcazioni e il mare aperto sullo sfondo.",
      "category": "panorama",
      "author": "Gabriella.c78",
      "source": "Wikimedia Commons",
      "source_url": "https://commons.wikimedia.org/wiki/File:Porto_di_Agropoli.jpg",
      "license": "CC BY-SA 4.0",
      "license_url": "https://creativecommons.org/licenses/by-sa/4.0/",
      "consulted_at": "2026-07-17",
      "alt": "Veduta dall'alto del porto turistico di Agropoli",
      "changes": "Ritaglio orizzontale 3:2, ridimensionamento a 1600 x 1067 pixel e conversione WebP.",
      "notes": "Opera derivata distribuita secondo i termini della licenza CC BY-SA 4.0; attribuzione all'autrice richiesta."
    },
    {
      "id": "IMG-ALBANELLA-CARD-001",
      "municipality": "Albanella",
      "file": "images/comuni/albanella.webp",
      "type": "card",
      "title": "Panorama di Albanella",
      "subject": "Veduta panoramica del capoluogo e delle colline di Albanella",
      "description": "Panorama orizzontale di Albanella nel paesaggio collinare.",
      "category": "panorama",
      "author": "Lobufalo",
      "source": "Wikimedia Commons",
      "source_url": "https://commons.wikimedia.org/wiki/File:Albanella_-_Panorama.jpeg",
      "license": "Pubblico dominio",
      "license_url": "https://creativecommons.org/publicdomain/mark/1.0/",
      "consulted_at": "2026-07-17",
      "alt": "Veduta panoramica del capoluogo e delle colline di Albanella",
      "changes": "Ritaglio orizzontale 8:5, ridimensionamento a 800 x 500 pixel e conversione WebP.",
      "notes": "Opera rilasciata nel pubblico dominio dall'autore."
    },
    {
      "id": "IMG-ALBANELLA-COVER-001",
      "municipality": "Albanella",
      "file": "images/comuni/albanella-santa-sofia.webp",
      "type": "cover",
      "title": "Santuario di Santa Sofia",
      "subject": "Facciata principale del Santuario di Santa Sofia ad Albanella",
      "description": "La facciata del santuario dedicato alla patrona di Albanella.",
      "category": "luoghi di culto",
      "author": "Lobufalo",
      "source": "Wikimedia Commons",
      "source_url": "https://commons.wikimedia.org/wiki/File:Albanella_-_Santuario_di_Santa_Sofia_3.jpeg",
      "license": "Pubblico dominio",
      "license_url": "https://creativecommons.org/publicdomain/mark/1.0/",
      "consulted_at": "2026-07-17",
      "alt": "Facciata principale del Santuario di Santa Sofia ad Albanella",
      "changes": "Ritaglio orizzontale 8:5, ridimensionamento a 800 x 500 pixel e conversione WebP.",
      "notes": "Opera rilasciata nel pubblico dominio dall'autore."
    },
    {
      "id": "IMG-ALBANELLA-GALLERY-001",
      "municipality": "Albanella",
      "file": "images/comuni/albanella-piazza-garibaldi.webp",
      "type": "gallery",
      "title": "Piazza Garibaldi",
      "subject": "Piazza Garibaldi nel centro di Albanella",
      "description": "La piazza del capoluogo conosciuta localmente anche come il Pozzillo.",
      "category": "centro storico",
      "author": "Lobufalo",
      "source": "Wikimedia Commons",
      "source_url": "https://commons.wikimedia.org/wiki/File:Albanella_-_Piazza_Garibaldi.jpeg",
      "license": "Pubblico dominio",
      "license_url": "https://creativecommons.org/publicdomain/mark/1.0/",
      "consulted_at": "2026-07-17",
      "alt": "Piazza Garibaldi nel centro di Albanella",
      "changes": "Ritaglio orizzontale 3:2, ridimensionamento a 1600 x 1067 pixel e conversione WebP.",
      "notes": "Opera rilasciata nel pubblico dominio dall'autore."
    },
    {
      "id": "IMG-ALBANELLA-GALLERY-002",
      "municipality": "Albanella",
      "file": "images/comuni/albanella-bosco-camerine.webp",
      "type": "gallery",
      "title": "Bosco Camerine",
      "subject": "Paesaggio rurale nella località Bosco Camerine",
      "description": "Una veduta del paesaggio nella località Bosco Camerine di Albanella.",
      "category": "paesaggio",
      "author": "Lobufalo",
      "source": "Wikimedia Commons",
      "source_url": "https://commons.wikimedia.org/wiki/File:Albanella_-_Bosco_Camerine.jpg",
      "license": "Pubblico dominio",
      "license_url": "https://creativecommons.org/publicdomain/mark/1.0/",
      "consulted_at": "2026-07-17",
      "alt": "Paesaggio rurale nella località Bosco Camerine di Albanella",
      "changes": "Ritaglio orizzontale 3:2, ridimensionamento a 1600 x 1067 pixel e conversione WebP.",
      "notes": "Opera rilasciata nel pubblico dominio dall'autore."
    },
    {
      "id": "IMG-ALBANELLA-GALLERY-003",
      "municipality": "Albanella",
      "file": "images/comuni/albanella-bosco-camerine-sentiero.webp",
      "type": "gallery",
      "title": "Sentiero di Bosco Camerine",
      "subject": "Sentiero escursionistico nell'Oasi di Bosco Camerine",
      "description": "Un tratto del percorso naturalistico all'interno dell'Oasi di Bosco Camerine.",
      "category": "natura",
      "author": "Lobufalo",
      "source": "Wikimedia Commons",
      "source_url": "https://commons.wikimedia.org/wiki/File:Bosco_Camerine_-_sentiero.jpg",
      "license": "Pubblico dominio",
      "license_url": "https://creativecommons.org/publicdomain/mark/1.0/",
      "consulted_at": "2026-07-17",
      "alt": "Sentiero escursionistico nell'Oasi di Bosco Camerine",
      "changes": "Ritaglio orizzontale 3:2, ridimensionamento a 1600 x 1067 pixel e conversione WebP.",
      "notes": "Opera rilasciata nel pubblico dominio dall'autore."
    },
    {
      "id": "IMG-ALBANELLA-GALLERY-004",
      "municipality": "Albanella",
      "file": "images/comuni/albanella-bosco-camerine-segnaletica.webp",
      "type": "gallery",
      "title": "Oasi di Bosco Camerine",
      "subject": "Segnaletica dell'Oasi naturalistica Bosco Camerine",
      "description": "La segnaletica che identifica l'area naturalistica di Bosco Camerine.",
      "category": "natura",
      "author": "Lobufalo",
      "source": "Wikimedia Commons",
      "source_url": "https://commons.wikimedia.org/wiki/File:Bosco_Camerine_-_segnaletica.jpg",
      "license": "Pubblico dominio",
      "license_url": "https://creativecommons.org/publicdomain/mark/1.0/",
      "consulted_at": "2026-07-17",
      "alt": "Segnaletica dell'Oasi naturalistica Bosco Camerine",
      "changes": "Ritaglio orizzontale 3:2, ridimensionamento a 1600 x 1067 pixel e conversione WebP.",
      "notes": "Opera rilasciata nel pubblico dominio dall'autore."
    }
  ]
}
